optimize_struct.py
optimize_struct_qe.py
predict_thickness_2D.py
read_write.py
write_inputs.py
thick2d-1.1.data/scripts/thick2d
thick2d-1.1.dist-info/LICENSE
thick2d-1.1.dist-info/METADATA
thick2d-1.1.dist-info/WHEEL
thick2d-1.1.dist-info/top_level.txt
thick2d-1.1.dist-info/RECORD
