Metadata-Version: 2.1
Name: thick2d
Version: 1.1
Summary: "THICK-2D -- Thickness Hierarchy Inference & Calculation Kit for 2D materials",
Home-page: https://sourceforge.net/projects/thick2d/
Author: Chinedu Ekuma
Author-email: cekuma1@gmail.com
License: GNU GPL version 3
License-File: LICENSE
Requires-Dist: numpy
Requires-Dist: scipy
Requires-Dist: matplotlib
Requires-Dist: pandas
Requires-Dist: spglib
Requires-Dist: ase
Requires-Dist: catboost
Requires-Dist: pymatgen
Requires-Dist: matminer
Requires-Dist: scikit-learn
Requires-Dist: tensorflow
Requires-Dist: keras
Requires-Dist: bayesian-optimization
